sphinx_hyperhelp/__init__.py
sphinx_hyperhelp/help_builder.py
sphinx_hyperhelp/help_writer.py
sphinx_hyperhelp/hyperhelp.py
sphinx_hyperhelp-0.1.0.dist-info/entry_points.txt
sphinx_hyperhelp-0.1.0.dist-info/LICENSE
sphinx_hyperhelp-0.1.0.dist-info/WHEEL
sphinx_hyperhelp-0.1.0.dist-info/METADATA
sphinx_hyperhelp-0.1.0.dist-info/RECORD
